js.url_parser-1.1.0-py2.7-nspkg.pth
js/url_parser/__init__.py
js/url_parser/test_url-parser.txt
js/url_parser/resources/url-parser.js
js/url_parser/resources/url-parser.min.js
js.url_parser-1.1.0.dist-info/DESCRIPTION.rst
js.url_parser-1.1.0.dist-info/entry_points.txt
js.url_parser-1.1.0.dist-info/METADATA
js.url_parser-1.1.0.dist-info/metadata.json
js.url_parser-1.1.0.dist-info/namespace_packages.txt
js.url_parser-1.1.0.dist-info/RECORD
js.url_parser-1.1.0.dist-info/top_level.txt
js.url_parser-1.1.0.dist-info/WHEEL
