Metadata-Version: 2.0
Name: js.url-parser
Version: 1.1.0
Summary: Fanstatic packaging of url-parser
Home-page: https://bitbucket.org/negval/js.url_parser
Author: Denis Sukhonin
Author-email: d.sukhonin@gmail.com
License: BSD
Keywords: fanstatic js javascript url parser
Platform: UNKNOWN
Requires-Dist: fanstatic
Requires-Dist: setuptools
